pyBCRAdata/__init__.py
pyBCRAdata/api_docs.json
pyBCRAdata/base_api.py
pyBCRAdata/client.py
pyBCRAdata/connector.py
pyBCRAdata/settings.py
pyBCRAdata/cert/ca.pem
pybcradata-0.4.3.dist-info/licenses/LICENSE
pybcradata-0.4.3.dist-info/METADATA
pybcradata-0.4.3.dist-info/WHEEL
pybcradata-0.4.3.dist-info/top_level.txt
pybcradata-0.4.3.dist-info/RECORD
