Metadata-Version: 2.4
Name: pyBCRAdata
Version: 0.4.3
Summary: Cliente Python para acceder a estadísticas monetarias, datos de tipo de cambio e información de deudores del Banco Central de la República Argentina (BCRA)
Author-email: Diego Mora <morabdiego@gmail.com>
License-Expression: LicenseRef-NonCommercial-1.0
Project-URL: Homepage, https://github.com/morabdiego/pyBCRA
Project-URL: Bug Tracker, https://github.com/morabdiego/pyBCRA/issues
Project-URL: Documentation, https://github.com/morabdiego/pyBCRA/tree/main/docs
Project-URL: Source Code, https://github.com/morabdiego/pyBCRA
Classifier: Development Status :: 4 - Beta
Classifier: Intended Audience :: Financial and Insurance Industry
Classifier: Intended Audience :: Science/Research
Classifier: Operating System :: OS Independent
Classifier: Programming Language :: Python :: 3
Classifier: Programming Language :: Python :: 3.8
Classifier: Programming Language :: Python :: 3.9
Classifier: Programming Language :: Python :: 3.10
Classifier: Programming Language :: Python :: 3.11
Classifier: Topic :: Office/Business :: Financial
Classifier: Topic :: Software Development :: Libraries :: Python Modules
Requires-Python: >=3.8
License-File: LICENSE
Requires-Dist: pandas>=1.0.0
Requires-Dist: requests>=2.25.0
Requires-Dist: typing-extensions>=4.0.0
Requires-Dist: pydantic>=2.0.0
Provides-Extra: dev
Requires-Dist: pytest; extra == "dev"
Requires-Dist: pytest-cov; extra == "dev"
Requires-Dist: build; extra == "dev"
Dynamic: license-file
